reflex/__init__.py
reflex/app.py
reflex/app_server.py
reflex/assets.py
reflex/common.py
reflex/errors.py
reflex/generated/app.js
reflex/generated/app.js.map
reflex/generated/index.html
reflex/generated/style.css
reflex/generated/style.css.map
reflex/hosted-assets/showdown.min.js
reflex/image_source.py
reflex/session.py
reflex/styling/__init__.py
reflex/styling/box_style.py
reflex/styling/color.py
reflex/styling/fills.py
reflex/styling/markdown_style.py
reflex/styling/text_style.py
reflex/theme.py
reflex/user_settings_module.py
reflex/validator.py
reflex/widgets/__init__.py
reflex/widgets/auto_form.py
reflex/widgets/button.py
reflex/widgets/column.py
reflex/widgets/container.py
reflex/widgets/dropdown.py
reflex/widgets/image.py
reflex/widgets/markdown_view.py
reflex/widgets/media_player.py
reflex/widgets/metadata.py
reflex/widgets/mouse_event_listener.py
reflex/widgets/plot.py
reflex/widgets/progress_circle.py
reflex/widgets/rectangle.py
reflex/widgets/row.py
reflex/widgets/stack.py
reflex/widgets/switch.py
reflex/widgets/text.py
reflex/widgets/text_input.py
reflex/widgets/widget_base.py
reflex/world_units.py
reflex_ui-0.1.6.dist-info/LICENSE.txt
reflex_ui-0.1.6.dist-info/METADATA
reflex_ui-0.1.6.dist-info/WHEEL
reflex_ui-0.1.6.dist-info/RECORD
